bumping/__init__.py
bumping/bumping.py
bumping/test.py
bumping-0.5.2.dist-info/LICENSE
bumping-0.5.2.dist-info/METADATA
bumping-0.5.2.dist-info/WHEEL
bumping-0.5.2.dist-info/entry_points.txt
bumping-0.5.2.dist-info/top_level.txt
bumping-0.5.2.dist-info/RECORD
