Metadata-Version: 2.1
Name: bumping
Version: 0.5.2
Summary: Python tool to calculate SemVer based on conventional git commit messages.
Home-page: https://github.com/WqyJh/bumping
Author: wqy
Author-email: qiyingwangwqy@gmail.com
License: UNKNOWN
Keywords: git,conventionalcommits,SemVer
Platform: UNKNOWN
Classifier: Programming Language :: Python :: 3 :: Only
Requires-Dist: gitpython
Requires-Dist: click
